django_supporttools-3.6.4.dist-info/licenses/LICENSE
supporttools/VERSION
supporttools/__init__.py
supporttools/context_processors.py
supporttools/urls.py
supporttools/views.py
supporttools/static/supporttools/css/.DS_Store
supporttools/static/supporttools/css/desktop.less
supporttools/static/supporttools/css/mobile.less
supporttools/static/supporttools/js/main.js
supporttools/static/uw/ico/android-196x196.png
supporttools/static/uw/ico/apple-touch-icon-114x114-precomposed.png
supporttools/static/uw/ico/apple-touch-icon-120x120-precomposed.png
supporttools/static/uw/ico/apple-touch-icon-144x144-precomposed.png
supporttools/static/uw/ico/apple-touch-icon-152x152-precomposed.png
supporttools/static/uw/ico/apple-touch-icon-180x180-precomposed.png
supporttools/static/uw/ico/apple-touch-icon-192x192-precomposed.png
supporttools/static/uw/ico/apple-touch-icon-57x57-precomposed.png
supporttools/static/uw/ico/apple-touch-icon-60x60-precomposed.png
supporttools/static/uw/ico/apple-touch-icon-72x72-precomposed.png
supporttools/static/uw/ico/apple-touch-icon-76x76-precomposed.png
supporttools/static/uw/ico/apple-touch-icon-precomposed.png
supporttools/static/uw/ico/favicon.ico
supporttools/static/uw/ico/win8-144x144.png
supporttools/static/uw/ico/win8-150x150.png
supporttools/static/uw/ico/win8-310x150.png
supporttools/static/uw/ico/win8-310x310.png
supporttools/static/uw/ico/win8-70x70.png
supporttools/static/vendor/fonts/FontAwesome.otf
supporttools/static/vendor/fonts/fontawesome-webfont.eot
supporttools/static/vendor/fonts/fontawesome-webfont.svg
supporttools/static/vendor/fonts/fontawesome-webfont.ttf
supporttools/static/vendor/fonts/fontawesome-webfont.woff
supporttools/static/vendor/fonts/glyphicons-halflings-regular.eot
supporttools/static/vendor/fonts/glyphicons-halflings-regular.svg
supporttools/static/vendor/fonts/glyphicons-halflings-regular.ttf
supporttools/static/vendor/fonts/glyphicons-halflings-regular.woff
supporttools/static/vendor/js/chart.min.js
supporttools/static/vendor/js/jquery-1.10.2.min.js
django_supporttools-3.6.4.dist-info/METADATA
django_supporttools-3.6.4.dist-info/WHEEL
django_supporttools-3.6.4.dist-info/top_level.txt
django_supporttools-3.6.4.dist-info/RECORD
