Metadata-Version: 2.4
Name: Django-SupportTools
Version: 3.6.4
Summary: A Django application used for theming and wrapping support tools.
Home-page: https://github.com/uw-it-aca/django-supporttools
Author: UW-IT Student & Educational Technology Services
Author-email: aca-it@uw.edu
License: Apache License, Version 2.0
Classifier: Intended Audience :: Developers
Classifier: License :: OSI Approved :: Apache Software License
Classifier: Operating System :: OS Independent
Classifier: Programming Language :: Python
License-File: LICENSE
Requires-Dist: django<6,>3.2
Requires-Dist: django-userservice
Requires-Dist: django-user-agents
Requires-Dist: mock
Dynamic: author
Dynamic: author-email
Dynamic: classifier
Dynamic: description
Dynamic: home-page
Dynamic: license
Dynamic: license-file
Dynamic: requires-dist
Dynamic: summary
